xlabml/__init__.py
xlabml/callbacks.py
xlabml/datamodules.py
xlabml/datasets.py
xlabml/inference.py
xlabml/models.py
xlabml/sched.py
xlabml/stats.py
xlabml/text.py
xlabml/tokenizer.py
xlabml/transformers.py
xlabml/utils.py
xlabml/tests/__init__.py
xlabml/tests/test_datasets.py
xlabml/tests/test_tokenizer.py
xlabml-0.2.0.dist-info/licenses/LICENSE
xlabml-0.2.0.dist-info/WHEEL
xlabml-0.2.0.dist-info/METADATA
xlabml-0.2.0.dist-info/RECORD
