Metadata-Version: 2.4
Name: xlabml
Version: 0.2.0
Summary: Transformer Lab - experimental implementations and training of transformer models at scale, using modern techniques
Author-email: Victor Semionov <vsemionov@gmail.com>
Requires-Python: >=3.10
License-Expression: Apache-2.0
License-File: LICENSE
Requires-Dist: boltons
Requires-Dist: click
Requires-Dist: datasets
Requires-Dist: jsonargparse[signatures]
Requires-Dist: lightning
Requires-Dist: numpy
Requires-Dist: omegaconf
Requires-Dist: python-dotenv
Requires-Dist: requests
Requires-Dist: rich
Requires-Dist: s3fs
Requires-Dist: sentencepiece
Requires-Dist: tensorboard
Requires-Dist: torch
Requires-Dist: torchdata
Requires-Dist: tqdm
Requires-Dist: flit ; extra == "dev"
Project-URL: Home, https://github.com/vsemionov/xlab
Provides-Extra: dev
